discord_rpc-5.5.dist-info/licenses/LICENSE
discordrpc/__init__.py
discordrpc/button.py
discordrpc/exceptions.py
discordrpc/presence.py
discordrpc/types.py
discordrpc/utils.py
discord_rpc-5.5.dist-info/METADATA
discord_rpc-5.5.dist-info/WHEEL
discord_rpc-5.5.dist-info/top_level.txt
discord_rpc-5.5.dist-info/RECORD
