Metadata-Version: 2.4
Name: discord-rpc
Version: 5.5
Summary: A Python wrapper for the Discord RPC API
Author-email: Senophyx <contact@senophyx.id>
License: MIT License
Project-URL: Homepage, https://github.com/Senophyx/discord-rpc
Project-URL: Documentation, https://github.com/Senophyx/Discord-RPC/blob/main/DOCS.md
Project-URL: Issue tracker, https://github.com/Senophyx/discord-rpc/issues
Project-URL: Discord, https://discord.gg/qpT2AeYZRN
Keywords: Discord,rpc,discord rpc
Classifier: Development Status :: 5 - Production/Stable
Classifier: Intended Audience :: Developers
Classifier: Intended Audience :: End Users/Desktop
Classifier: Intended Audience :: Other Audience
Classifier: Programming Language :: Python :: 3.7
Classifier: Programming Language :: Python :: 3.8
Classifier: Programming Language :: Python :: 3.9
Classifier: Programming Language :: Python :: 3.10
Classifier: License :: OSI Approved :: MIT License
Classifier: Operating System :: Microsoft :: Windows
Classifier: Operating System :: MacOS
Classifier: Operating System :: POSIX :: Linux
Classifier: Programming Language :: Python
Requires-Python: >=3.7
License-File: LICENSE
Dynamic: license-file
